ferenda/__init__.py
ferenda/citationparser.py
ferenda/citationpatterns.py
ferenda/compat.py
ferenda/compositerepository.py
ferenda/decorators.py
ferenda/describer.py
ferenda/devel.py
ferenda/document.py
ferenda/documententry.py
ferenda/documentrepository.py
ferenda/documentstore.py
ferenda/errors.py
ferenda/facet.py
ferenda/feed.py
ferenda/feedset.py
ferenda/fsmparser.py
ferenda/fulltextindex.py
ferenda/manager.py
ferenda/pdfanalyze.py
ferenda/pdfdocumentrepository.py
ferenda/pdfreader.py
ferenda/resources.py
ferenda/testutil.py
ferenda/textreader.py
ferenda/tocpage.py
ferenda/tocpageset.py
ferenda/transformer.py
ferenda/triplestore.py
ferenda/uriformats.py
ferenda/uriformatter.py
ferenda/util.py
ferenda/wordreader.py
ferenda/wsgiapp.py
ferenda/elements/__init__.py
ferenda/elements/elements.py
ferenda/elements/html.py
ferenda/res/humans.txt
ferenda/res/robots.txt
ferenda/res/css/ferenda.css
ferenda/res/css/main.css
ferenda/res/css/normalize-1.1.3.css
ferenda/res/css/pdfview.css
ferenda/res/css/sfs.css
ferenda/res/css/print/print-2col.css
ferenda/res/css/print/README.txt
ferenda/res/css/print/xht2-print.css
ferenda/res/css/print/xhtml.css
ferenda/res/etc/base.ebnf
ferenda/res/etc/eglag.ebnf
ferenda/res/etc/egratt.ebnf
ferenda/res/etc/forarbeten.ebnf
ferenda/res/etc/kortlagrum.ebnf
ferenda/res/etc/lagrum.ebnf
ferenda/res/etc/rattsfall.ebnf
ferenda/res/etc/sfs-extra.n3
ferenda/res/eut/goldstandard.n3
ferenda/res/eut/sameas.n3
ferenda/res/extra/base.ttl
ferenda/res/extra/rfc.ttl
ferenda/res/extra/sfs.ttl
ferenda/res/extra/swedishlegalsource.ttl
ferenda/res/extra/w3c.ttl
ferenda/res/img/navmenu-small-black.png
ferenda/res/img/navmenu.png
ferenda/res/img/search.png
ferenda/res/js/ferenda.js
ferenda/res/js/jquery-1.10.2.js
ferenda/res/js/modernizr-2.6.3.js
ferenda/res/js/pdfviewer.js
ferenda/res/js/respond-1.3.0.js
ferenda/res/scripts/ferenda-build.py
ferenda/res/scripts/ferenda.template.ini
ferenda-0.3.0.dist-info/DESCRIPTION.rst
ferenda-0.3.0.dist-info/entry_points.txt
ferenda-0.3.0.dist-info/METADATA
ferenda-0.3.0.dist-info/metadata.json
ferenda-0.3.0.dist-info/RECORD
ferenda-0.3.0.dist-info/top_level.txt
ferenda-0.3.0.dist-info/WHEEL
