Metadata-Version: 2.0
Name: ferenda
Version: 0.3.0
Summary: Transform unstructured document collections to structured Linked Data
Home-page: https://github.com/staffanm/ferenda/
Author: Staffan Malmgren
Author-email: staffan.malmgren@gmail.com
License: BSD
Keywords: rdf linkeddata parsing
Platform: UNKNOWN
Classifier: Development Status :: 3 - Alpha
Classifier: Environment :: Console
Classifier: Environment :: Web Environment
Classifier: Intended Audience :: Developers
Classifier: License :: OSI Approved :: BSD License
Classifier: Operating System :: OS Independent
Classifier: Programming Language :: Python
Classifier: Programming Language :: Python :: 2
Classifier: Programming Language :: Python :: 2.6
Classifier: Programming Language :: Python :: 2.7
Classifier: Programming Language :: Python :: 3
Classifier: Programming Language :: Python :: 3.2
Classifier: Programming Language :: Python :: 3.3
Classifier: Programming Language :: Python :: 3.4
Classifier: Topic :: Software Development :: Libraries :: Python Modules
Classifier: Topic :: Internet :: WWW/HTTP :: WSGI :: Application
Classifier: Topic :: Text Processing
Classifier: Topic :: Text Processing :: Indexing
Classifier: Topic :: Text Processing :: Markup :: XML
Requires-Dist: beautifulsoup4 (>=4.3.0)
Requires-Dist: jsmin (>=2.0.2)
Requires-Dist: cssmin (>=0.2.0)
Requires-Dist: lxml (>=3.2.0)
Requires-Dist: rdflib (>=4.0.1)
Requires-Dist: html5lib (>=1.0b1)
Requires-Dist: rdfextras (>=0.4)
Requires-Dist: rdflib-jsonld (>=0.2)
Requires-Dist: requests (>=1.2.0)
Requires-Dist: Whoosh (>=2.4.1)
Requires-Dist: six (>=1.4.0)
Requires-Dist: docutils (>=0.11)
Requires-Dist: layeredconfig (>=0.2.1)
Requires-Dist: responses (>=0.3.0)
Requires-Dist: pyparsing
Requires-Dist: grako (>=3.4.0)
